{
    "sample0": {
        "f_0": 0.482,
        "f_1": 0.508,
        "f_2": 0.441,
        "f_3": 0.436,
        "f_4": 0.431,
        "f_5": 0.453,
        "f_6": 0.398,
        "f_7": 0.376,
        "f_8": 0.371,
        "f_9": 0.355,
        "f_10": 0.366,
        "f_11": 0.333
    },
    "sample1": {
        "f_0": 0.509,
        "f_1": 0.532,
        "f_2": 0.545,
        "f_3": 0.574,
        "f_4": 0.569,
        "f_5": 0.542,
        "f_6": 0.518,
        "f_7": 0.496,
        "f_8": 0.438,
        "f_9": 0.428,
        "f_10": 0.365,
        "f_11": 0.329
    },
    "sample2": {
        "f_0": 0.511,
        "f_1": 0.523,
        "f_2": 0.583,
        "f_3": 0.587,
        "f_4": 0.612,
        "f_5": 0.642,
        "f_6": 0.656,
        "f_7": 0.659,
        "f_8": 0.677,
        "f_9": 0.654,
        "f_10": 0.678,
        "f_11": 0.654
    },
    "sample3": {
        "f_0": 0.47,
        "f_1": 0.552,
        "f_2": 0.559,
        "f_3": 0.617,
        "f_4": 0.665,
        "f_5": 0.654,
        "f_6": 0.697,
        "f_7": 0.718,
        "f_8": 0.727,
        "f_9": 0.736,
        "f_10": 0.744,
        "f_11": 0.713
    },
    "sample4": {
        "f_0": 0.526,
        "f_1": 0.496,
        "f_2": 0.527,
        "f_3": 0.488,
        "f_4": 0.499,
        "f_5": 0.497,
        "f_6": 0.46,
        "f_7": 0.481,
        "f_8": 0.443,
        "f_9": 0.447,
        "f_10": 0.437,
        "f_11": 0.434
    },
    "sample5": {
        "f_0": 0.508,
        "f_1": 0.58,
        "f_2": 0.609,
        "f_3": 0.652,
        "f_4": 0.692,
        "f_5": 0.716,
        "f_6": 0.712,
        "f_7": 0.676,
        "f_8": 0.679,
        "f_9": 0.641,
        "f_10": 0.624,
        "f_11": 0.572
    },
    "sample6": {
        "f_0": 0.451,
        "f_1": 0.541,
        "f_2": 0.572,
        "f_3": 0.603,
        "f_4": 0.622,
        "f_5": 0.626,
        "f_6": 0.623,
        "f_7": 0.634,
        "f_8": 0.664,
        "f_9": 0.672,
        "f_10": 0.643,
        "f_11": 0.645
    },
    "sample7": {
        "f_0": 0.492,
        "f_1": 0.551,
        "f_2": 0.538,
        "f_3": 0.599,
        "f_4": 0.563,
        "f_5": 0.565,
        "f_6": 0.596,
        "f_7": 0.606,
        "f_8": 0.611,
        "f_9": 0.585,
        "f_10": 0.617,
        "f_11": 0.635
    },
    "sample8": {
        "f_0": 0.496,
        "f_1": 0.459,
        "f_2": 0.382,
        "f_3": 0.348,
        "f_4": 0.309,
        "f_5": 0.257,
        "f_6": 0.191,
        "f_7": 0.167,
        "f_8": 0.13,
        "f_9": 0.102,
        "f_10": 0.09,
        "f_11": 0.098
    },
    "sample9": {
        "f_0": 0.497,
        "f_1": 0.449,
        "f_2": 0.373,
        "f_3": 0.317,
        "f_4": 0.272,
        "f_5": 0.239,
        "f_6": 0.158,
        "f_7": 0.117,
        "f_8": 0.075,
        "f_9": 0.068,
        "f_10": 0.065,
        "f_11": 0.068
    },
    "sample10": {
        "f_0": 0.489,
        "f_1": 0.452,
        "f_2": 0.441,
        "f_3": 0.397,
        "f_4": 0.371,
        "f_5": 0.317,
        "f_6": 0.294,
        "f_7": 0.247,
        "f_8": 0.209,
        "f_9": 0.192,
        "f_10": 0.179,
        "f_11": 0.145
    },
    "sample11": {
        "f_0": 0.489,
        "f_1": 0.445,
        "f_2": 0.373,
        "f_3": 0.349,
        "f_4": 0.294,
        "f_5": 0.252,
        "f_6": 0.208,
        "f_7": 0.153,
        "f_8": 0.134,
        "f_9": 0.077,
        "f_10": 0.074,
        "f_11": 0.059
    },
    "sample12": {
        "f_0": 0.501,
        "f_1": 0.473,
        "f_2": 0.439,
        "f_3": 0.363,
        "f_4": 0.342,
        "f_5": 0.293,
        "f_6": 0.275,
        "f_7": 0.232,
        "f_8": 0.2,
        "f_9": 0.172,
        "f_10": 0.142,
        "f_11": 0.109
    },
    "sample13": {
        "f_0": 0.487,
        "f_1": 0.519,
        "f_2": 0.513,
        "f_3": 0.557,
        "f_4": 0.521,
        "f_5": 0.572,
        "f_6": 0.595,
        "f_7": 0.593,
        "f_8": 0.575,
        "f_9": 0.592,
        "f_10": 0.64,
        "f_11": 0.603
    },
    "sample14": {
        "f_0": 0.494,
        "f_1": 0.532,
        "f_2": 0.546,
        "f_3": 0.599,
        "f_4": 0.61,
        "f_5": 0.604,
        "f_6": 0.644,
        "f_7": 0.633,
        "f_8": 0.656,
        "f_9": 0.648,
        "f_10": 0.65,
        "f_11": 0.664
    },
    "sample15": {
        "f_0": 0.508,
        "f_1": 0.566,
        "f_2": 0.627,
        "f_3": 0.66,
        "f_4": 0.681,
        "f_5": 0.707,
        "f_6": 0.735,
        "f_7": 0.7,
        "f_8": 0.651,
        "f_9": 0.632,
        "f_10": 0.595,
        "f_11": 0.467
    },
    "sample16": {
        "f_0": 0.51,
        "f_1": 0.57,
        "f_2": 0.553,
        "f_3": 0.637,
        "f_4": 0.634,
        "f_5": 0.639,
        "f_6": 0.679,
        "f_7": 0.723,
        "f_8": 0.739,
        "f_9": 0.752,
        "f_10": 0.745,
        "f_11": 0.773
    },
    "sample17": {
        "f_0": 0.484,
        "f_1": 0.471,
        "f_2": 0.452,
        "f_3": 0.393,
        "f_4": 0.376,
        "f_5": 0.315,
        "f_6": 0.274,
        "f_7": 0.246,
        "f_8": 0.226,
        "f_9": 0.223,
        "f_10": 0.227,
        "f_11": 0.254
    },
    "sample18": {
        "f_0": 0.498,
        "f_1": 0.518,
        "f_2": 0.54,
        "f_3": 0.595,
        "f_4": 0.584,
        "f_5": 0.541,
        "f_6": 0.556,
        "f_7": 0.559,
        "f_8": 0.51,
        "f_9": 0.482,
        "f_10": 0.494,
        "f_11": 0.488
    },
    "sample19": {
        "f_0": 0.488,
        "f_1": 0.571,
        "f_2": 0.609,
        "f_3": 0.614,
        "f_4": 0.681,
        "f_5": 0.715,
        "f_6": 0.742,
        "f_7": 0.713,
        "f_8": 0.728,
        "f_9": 0.748,
        "f_10": 0.714,
        "f_11": 0.728
    },
    "sample20": {
        "f_0": 0.507,
        "f_1": 0.447,
        "f_2": 0.383,
        "f_3": 0.31,
        "f_4": 0.251,
        "f_5": 0.226,
        "f_6": 0.148,
        "f_7": 0.117,
        "f_8": 0.07,
        "f_9": 0.054,
        "f_10": 0.037,
        "f_11": 0.048
    },
    "sample21": {
        "f_0": 0.513,
        "f_1": 0.488,
        "f_2": 0.473,
        "f_3": 0.465,
        "f_4": 0.438,
        "f_5": 0.422,
        "f_6": 0.382,
        "f_7": 0.38,
        "f_8": 0.355,
        "f_9": 0.323,
        "f_10": 0.301,
        "f_11": 0.287
    },
    "sample22": {
        "f_0": 0.496,
        "f_1": 0.495,
        "f_2": 0.492,
        "f_3": 0.494,
        "f_4": 0.507,
        "f_5": 0.473,
        "f_6": 0.452,
        "f_7": 0.463,
        "f_8": 0.399,
        "f_9": 0.379,
        "f_10": 0.33,
        "f_11": 0.353
    },
    "sample23": {
        "f_0": 0.491,
        "f_1": 0.543,
        "f_2": 0.541,
        "f_3": 0.608,
        "f_4": 0.616,
        "f_5": 0.634,
        "f_6": 0.653,
        "f_7": 0.656,
        "f_8": 0.672,
        "f_9": 0.695,
        "f_10": 0.633,
        "f_11": 0.658
    },
    "sample24": {
        "f_0": 0.513,
        "f_1": 0.534,
        "f_2": 0.554,
        "f_3": 0.519,
        "f_4": 0.612,
        "f_5": 0.631,
        "f_6": 0.651,
        "f_7": 0.641,
        "f_8": 0.663,
        "f_9": 0.686,
        "f_10": 0.679,
        "f_11": 0.666
    },
    "sample25": {
        "f_0": 0.502,
        "f_1": 0.518,
        "f_2": 0.542,
        "f_3": 0.573,
        "f_4": 0.589,
        "f_5": 0.574,
        "f_6": 0.574,
        "f_7": 0.57,
        "f_8": 0.574,
        "f_9": 0.568,
        "f_10": 0.571,
        "f_11": 0.558
    },
    "sample26": {
        "f_0": 0.463,
        "f_1": 0.459,
        "f_2": 0.454,
        "f_3": 0.423,
        "f_4": 0.418,
        "f_5": 0.375,
        "f_6": 0.348,
        "f_7": 0.324,
        "f_8": 0.329,
        "f_9": 0.305,
        "f_10": 0.284,
        "f_11": 0.238
    },
    "sample27": {
        "f_0": 0.512,
        "f_1": 0.484,
        "f_2": 0.463,
        "f_3": 0.438,
        "f_4": 0.365,
        "f_5": 0.362,
        "f_6": 0.36,
        "f_7": 0.35,
        "f_8": 0.32,
        "f_9": 0.306,
        "f_10": 0.306,
        "f_11": 0.308
    },
    "sample28": {
        "f_0": 0.496,
        "f_1": 0.542,
        "f_2": 0.597,
        "f_3": 0.637,
        "f_4": 0.665,
        "f_5": 0.696,
        "f_6": 0.7,
        "f_7": 0.725,
        "f_8": 0.73,
        "f_9": 0.741,
        "f_10": 0.715,
        "f_11": 0.716
    },
    "sample29": {
        "f_0": 0.487,
        "f_1": 0.577,
        "f_2": 0.614,
        "f_3": 0.66,
        "f_4": 0.69,
        "f_5": 0.702,
        "f_6": 0.692,
        "f_7": 0.723,
        "f_8": 0.718,
        "f_9": 0.667,
        "f_10": 0.689,
        "f_11": 0.616
    },
    "sample30": {
        "f_0": 0.507,
        "f_1": 0.501,
        "f_2": 0.52,
        "f_3": 0.5,
        "f_4": 0.482,
        "f_5": 0.501,
        "f_6": 0.472,
        "f_7": 0.458,
        "f_8": 0.425,
        "f_9": 0.444,
        "f_10": 0.387,
        "f_11": 0.408
    },
    "sample31": {
        "f_0": 0.497,
        "f_1": 0.523,
        "f_2": 0.513,
        "f_3": 0.532,
        "f_4": 0.506,
        "f_5": 0.509,
        "f_6": 0.519,
        "f_7": 0.539,
        "f_8": 0.525,
        "f_9": 0.465,
        "f_10": 0.474,
        "f_11": 0.444
    },
    "sample32": {
        "f_0": 0.502,
        "f_1": 0.509,
        "f_2": 0.538,
        "f_3": 0.506,
        "f_4": 0.482,
        "f_5": 0.473,
        "f_6": 0.466,
        "f_7": 0.421,
        "f_8": 0.419,
        "f_9": 0.404,
        "f_10": 0.386,
        "f_11": 0.377
    },
    "sample33": {
        "f_0": 0.5,
        "f_1": 0.538,
        "f_2": 0.552,
        "f_3": 0.583,
        "f_4": 0.604,
        "f_5": 0.63,
        "f_6": 0.606,
        "f_7": 0.62,
        "f_8": 0.585,
        "f_9": 0.569,
        "f_10": 0.541,
        "f_11": 0.497
    },
    "sample34": {
        "f_0": 0.492,
        "f_1": 0.507,
        "f_2": 0.52,
        "f_3": 0.492,
        "f_4": 0.478,
        "f_5": 0.477,
        "f_6": 0.429,
        "f_7": 0.43,
        "f_8": 0.41,
        "f_9": 0.414,
        "f_10": 0.396,
        "f_11": 0.368
    },
    "sample35": {
        "f_0": 0.497,
        "f_1": 0.406,
        "f_2": 0.351,
        "f_3": 0.272,
        "f_4": 0.174,
        "f_5": 0.14,
        "f_6": 0.095,
        "f_7": 0.062,
        "f_8": 0.031,
        "f_9": 0.04,
        "f_10": 0.046,
        "f_11": 0.071
    },
    "sample36": {
        "f_0": 0.506,
        "f_1": 0.466,
        "f_2": 0.503,
        "f_3": 0.441,
        "f_4": 0.435,
        "f_5": 0.375,
        "f_6": 0.359,
        "f_7": 0.349,
        "f_8": 0.319,
        "f_9": 0.282,
        "f_10": 0.254,
        "f_11": 0.249
    },
    "sample37": {
        "f_0": 0.513,
        "f_1": 0.503,
        "f_2": 0.504,
        "f_3": 0.5,
        "f_4": 0.462,
        "f_5": 0.428,
        "f_6": 0.41,
        "f_7": 0.379,
        "f_8": 0.371,
        "f_9": 0.353,
        "f_10": 0.309,
        "f_11": 0.293
    },
    "sample38": {
        "f_0": 0.501,
        "f_1": 0.505,
        "f_2": 0.478,
        "f_3": 0.455,
        "f_4": 0.467,
        "f_5": 0.426,
        "f_6": 0.395,
        "f_7": 0.385,
        "f_8": 0.33,
        "f_9": 0.351,
        "f_10": 0.295,
        "f_11": 0.292
    },
    "sample39": {
        "f_0": 0.502,
        "f_1": 0.55,
        "f_2": 0.614,
        "f_3": 0.681,
        "f_4": 0.699,
        "f_5": 0.729,
        "f_6": 0.706,
        "f_7": 0.715,
        "f_8": 0.659,
        "f_9": 0.646,
        "f_10": 0.594,
        "f_11": 0.576
    },
    "sample40": {
        "f_0": 0.495,
        "f_1": 0.537,
        "f_2": 0.576,
        "f_3": 0.573,
        "f_4": 0.621,
        "f_5": 0.637,
        "f_6": 0.652,
        "f_7": 0.639,
        "f_8": 0.642,
        "f_9": 0.685,
        "f_10": 0.631,
        "f_11": 0.618
    },
    "sample41": {
        "f_0": 0.479,
        "f_1": 0.548,
        "f_2": 0.58,
        "f_3": 0.58,
        "f_4": 0.643,
        "f_5": 0.655,
        "f_6": 0.676,
        "f_7": 0.675,
        "f_8": 0.672,
        "f_9": 0.7,
        "f_10": 0.704,
        "f_11": 0.672
    },
    "sample42": {
        "f_0": 0.49,
        "f_1": 0.485,
        "f_2": 0.476,
        "f_3": 0.479,
        "f_4": 0.488,
        "f_5": 0.458,
        "f_6": 0.417,
        "f_7": 0.462,
        "f_8": 0.403,
        "f_9": 0.372,
        "f_10": 0.408,
        "f_11": 0.37
    },
    "sample43": {
        "f_0": 0.497,
        "f_1": 0.544,
        "f_2": 0.547,
        "f_3": 0.618,
        "f_4": 0.633,
        "f_5": 0.679,
        "f_6": 0.645,
        "f_7": 0.692,
        "f_8": 0.663,
        "f_9": 0.675,
        "f_10": 0.663,
        "f_11": 0.644
    },
    "sample44": {
        "f_0": 0.492,
        "f_1": 0.55,
        "f_2": 0.566,
        "f_3": 0.541,
        "f_4": 0.57,
        "f_5": 0.575,
        "f_6": 0.565,
        "f_7": 0.558,
        "f_8": 0.542,
        "f_9": 0.533,
        "f_10": 0.493,
        "f_11": 0.486
    },
    "sample45": {
        "f_0": 0.484,
        "f_1": 0.545,
        "f_2": 0.625,
        "f_3": 0.652,
        "f_4": 0.677,
        "f_5": 0.725,
        "f_6": 0.73,
        "f_7": 0.725,
        "f_8": 0.719,
        "f_9": 0.724,
        "f_10": 0.744,
        "f_11": 0.71
    },
    "sample46": {
        "f_0": 0.502,
        "f_1": 0.427,
        "f_2": 0.394,
        "f_3": 0.343,
        "f_4": 0.323,
        "f_5": 0.266,
        "f_6": 0.234,
        "f_7": 0.203,
        "f_8": 0.164,
        "f_9": 0.137,
        "f_10": 0.104,
        "f_11": 0.082
    },
    "sample47": {
        "f_0": 0.508,
        "f_1": 0.471,
        "f_2": 0.475,
        "f_3": 0.42,
        "f_4": 0.398,
        "f_5": 0.401,
        "f_6": 0.339,
        "f_7": 0.332,
        "f_8": 0.293,
        "f_9": 0.303,
        "f_10": 0.321,
        "f_11": 0.301
    },
    "sample48": {
        "f_0": 0.502,
        "f_1": 0.548,
        "f_2": 0.576,
        "f_3": 0.581,
        "f_4": 0.573,
        "f_5": 0.585,
        "f_6": 0.642,
        "f_7": 0.634,
        "f_8": 0.612,
        "f_9": 0.577,
        "f_10": 0.56,
        "f_11": 0.565
    },
    "sample49": {
        "f_0": 0.497,
        "f_1": 0.531,
        "f_2": 0.564,
        "f_3": 0.58,
        "f_4": 0.59,
        "f_5": 0.598,
        "f_6": 0.636,
        "f_7": 0.631,
        "f_8": 0.652,
        "f_9": 0.651,
        "f_10": 0.638,
        "f_11": 0.667
    },
    "sample50": {
        "f_0": 0.513,
        "f_1": 0.524,
        "f_2": 0.559,
        "f_3": 0.549,
        "f_4": 0.561,
        "f_5": 0.588,
        "f_6": 0.569,
        "f_7": 0.569,
        "f_8": 0.571,
        "f_9": 0.625,
        "f_10": 0.605,
        "f_11": 0.587
    },
    "sample51": {
        "f_0": 0.521,
        "f_1": 0.436,
        "f_2": 0.413,
        "f_3": 0.336,
        "f_4": 0.284,
        "f_5": 0.221,
        "f_6": 0.189,
        "f_7": 0.142,
        "f_8": 0.086,
        "f_9": 0.088,
        "f_10": 0.052,
        "f_11": 0.049
    },
    "sample52": {
        "f_0": 0.499,
        "f_1": 0.558,
        "f_2": 0.599,
        "f_3": 0.649,
        "f_4": 0.64,
        "f_5": 0.661,
        "f_6": 0.689,
        "f_7": 0.712,
        "f_8": 0.668,
        "f_9": 0.696,
        "f_10": 0.66,
        "f_11": 0.596
    },
    "sample53": {
        "f_0": 0.48,
        "f_1": 0.495,
        "f_2": 0.481,
        "f_3": 0.432,
        "f_4": 0.408,
        "f_5": 0.345,
        "f_6": 0.331,
        "f_7": 0.28,
        "f_8": 0.251,
        "f_9": 0.268,
        "f_10": 0.225,
        "f_11": 0.242
    },
    "sample54": {
        "f_0": 0.505,
        "f_1": 0.459,
        "f_2": 0.402,
        "f_3": 0.352,
        "f_4": 0.297,
        "f_5": 0.263,
        "f_6": 0.205,
        "f_7": 0.152,
        "f_8": 0.12,
        "f_9": 0.089,
        "f_10": 0.064,
        "f_11": 0.058
    }
}