{"0": "cwyby7g2ac5g008jnvzg", "1": "cwyby815v39g008hzepg", "2": "cwyby8hehebg008jqx80", "3": "cwyby91997wg008y6vhg", "4": "cwyby99ehebg008jqx8g", "5": "cwyby9s2ac5g008jnw00", "6": "cwybya95v39g008hzeq0", "7": "cwybyah997wg008y6vj0", "8": "cwybyb1tdtng0087n8bg", "9": "cwybybh997wg008y6vk0", "10": "cwybyc1997wg008y6vkg", "11": "cwybyc92ac5g008jnw20", "12": "cwybycs2ac5g008jnw30", "13": "cwybyd95v39g008hzer0", "14": "cwybydhtdtng0087n8d0", "15": "cwybye1tdtng0087n8dg", "16": "cwybyeh2ac5g008jnw3g", "17": "cwybyf15v39g008hzerg", "18": "cwybyf9997wg008y6vm0", "19": "cwybyfs60bqg008q038g", "20": "cwybyga5v39g008hzes0", "21": "cwybygt997wg008y6vng", "22": "cwybyhatdtng0087n8h0", "23": "cwybyhj60bqg008q039g", "24": "cwybyj260bqg008q03a0", "25": "cwybyjj5v39g008hzetg", "26": "cwybyjt5v39g008hzev0", "27": "cwybykaehebg008jqxbg", "28": "cwybykt2ac5g008jnw4g", "29": "cwybym260bqg008q03b0", "30": "cwybymj5v39g008hzewg", "31": "cwybyn2ehebg008jqxc0", "32": "cwybynj5v39g008hzex0", "33": "cwybyp260bqg008q03bg", "34": "cwybypj60bqg008q03c0", "35": "cwybypttdtng0087n8j0", "36": "cwybyqa997wg008y6vpg", "37": "cwybyqtehebg008jqxcg", "38": "cwybyrb60bqg008q03dg", "39": "cwybyrk60bqg008q03e0", "40": "cwybys32ac5g008jnw60", "41": "cwybyskehebg008jqxdg", "42": "cwybyt3997wg008y6vr0", "43": "cwybytk997wg008y6vrg", "44": "cwybyv32ac5g008jnw6g", "45": "cwybyvk2ac5g008jnw7g", "46": "cwybyvv60bqg008q03f0", "47": "cwybywbehebg008jqxeg", "48": "cwybywv997wg008y6vs0", "49": "cwybyxbtdtng0087n8k0", "50": "cwybyxk2ac5g008jnw80", "51": "cwybyy35v39g008hzey0", "52": "cwybyykehebg008jqxf0", "53": "cwybyz360bqg008q03fg", "54": "cwybyzbehebg008jqxfg", "55": "cwybyzv60bqg008q03g0", "56": "cwybz0ctdtng0087n8kg", "57": "cwybz0w2ac5g008jnwa0", "58": "cwybz14997wg008y6vt0", "59": "cwybz1m2ac5g008jnwag", "60": "cwybz242ac5g008jnwb0", "61": "cwybz2c5v39g008hzeyg", "62": "cwybz2w997wg008y6vv0", "63": "cwybz3c2ac5g008jnwbg", "64": "cwybz3w60bqg008q03h0", "65": "cwybz4c997wg008y6vw0", "66": "cwybz4m5v39g008hzez0", "67": "cwybz5460bqg008q03j0", "68": "cwybz5wtdtng0087n8mg", "69": "cwybz64tdtng0087n8n0", "70": "cwybz6m997wg008y6vxg", "71": "cwybz74ehebg008jqxg0", "72": "cwybz7m60bqg008q03k0", "73": "cwybz7wehebg008jqxgg", "74": "cwybz8dehebg008jqxh0", "75": "cwybz8x997wg008y6vy0", "76": "cwybz95tdtng0087n8q0", "77": "cwybz9n5v39g008hzf30", "78": "cwybza5997wg008y6vz0", "79": "cwybzan60bqg008q03pg", "80": "cwybzbn2ac5g008jnwdg", "81": "cwybzc52ac5g008jnwe0", "82": "cwybzcnehebg008jqxj0", "83": "cwybzd52ac5g008jnweg", "84": "cwybzdd2ac5g008jnwf0", "85": "cwybzdx2ac5g008jnwfg", "86": "cwybzedtdtng0087n8r0", "87": "cwybzen997wg008y6w0g", "88": "cwybzf5tdtng0087n8rg", "89": "cwybzfn997wg008y6w10", "90": "cwybzfx2ac5g008jnwg0", "91": "cwybzgeehebg008jqxk0", "92": "cwybzgyehebg008jqxkg", "93": "cwybzhe5v39g008hzf60", "94": "cwybzhp2ac5g008jnwh0", "95": "cwybzj6997wg008y6w20", "96": "cwybzjp997wg008y6w2g", "97": "cwybzk6997wg008y6w30", "98": "cwybzke997wg008y6w3g", "99": "cwybzkytdtng0087n8sg", "100": "cwybzme5v39g008hzf70", "101": "cwybzmyehebg008jqxng", "102": "cwybzn660bqg008q03sg", "103": "cwybznp2ac5g008jnwmg", "104": "cwybzp6ehebg008jqxpg", "105": "cwybzpp5v39g008hzf7g", "106": "cwybzpy5v39g008hzf90", "107": "cwybzqe2ac5g008jnwn0", "108": "cwybzqy60bqg008q03vg", "109": "cwybzr7ehebg008jqxq0", "110": "cwybzrq2ac5g008jnwp0", "111": "cwybzs7997wg008y6w5g", "112": "cwybzsf997wg008y6w6g", "113": "cwybzsztdtng0087n8vg", "114": "cwybztftdtng0087n8wg", "115": "cwybztqehebg008jqxqg", "116": "cwybzv7tdtng0087n8xg", "117": "cwybzvq60bqg008q03x0", "118": "cwybzvz60bqg008q03xg", "119": "cwybzwf2ac5g008jnwqg"}